MANIFEST.in
README.md
setup.cfg
setup.py
dsreports/__init__.py
dsreports/__main__.py
dsreports.egg-info/PKG-INFO
dsreports.egg-info/SOURCES.txt
dsreports.egg-info/dependency_links.txt
dsreports.egg-info/not-zip-safe
dsreports.egg-info/top_level.txt
dsreports/site/.project
dsreports/site/config.toml
dsreports/site/.settings/.jsdtscope
dsreports/site/.settings/org.eclipse.wst.common.component
dsreports/site/.settings/org.eclipse.wst.common.project.facet.core.xml
dsreports/site/.settings/org.eclipse.wst.jsdt.ui.superType.container
dsreports/site/.settings/org.eclipse.wst.jsdt.ui.superType.name
dsreports/site/layouts/index.html
dsreports/site/layouts/partials/footer.html
dsreports/site/layouts/partials/head.html
dsreports/site/layouts/partials/header.html
dsreports/site/static/css/bokeh.css
dsreports/site/static/css/screen.css
dsreports/site/static/css/bulma/bulma.css
dsreports/site/static/css/bulma/bulma.css.map
dsreports/site/static/css/bulma/bulmasuite.css
dsreports/site/static/css/font-awesome/HELP-US-OUT.txt
dsreports/site/static/css/font-awesome/css/font-awesome.css
dsreports/site/static/css/font-awesome/css/font-awesome.min.css
dsreports/site/static/css/font-awesome/fonts/FontAwesome.otf
dsreports/site/static/css/font-awesome/fonts/fontawesome-webfont.eot
dsreports/site/static/css/font-awesome/fonts/fontawesome-webfont.svg
dsreports/site/static/css/font-awesome/fonts/fontawesome-webfont.ttf
dsreports/site/static/css/font-awesome/fonts/fontawesome-webfont.woff
dsreports/site/static/css/font-awesome/fonts/fontawesome-webfont.woff2
dsreports/site/static/css/font-awesome/less/animated.less
dsreports/site/static/css/font-awesome/less/bordered-pulled.less
dsreports/site/static/css/font-awesome/less/core.less
dsreports/site/static/css/font-awesome/less/fixed-width.less
dsreports/site/static/css/font-awesome/less/font-awesome.less
dsreports/site/static/css/font-awesome/less/icons.less
dsreports/site/static/css/font-awesome/less/larger.less
dsreports/site/static/css/font-awesome/less/list.less
dsreports/site/static/css/font-awesome/less/mixins.less
dsreports/site/static/css/font-awesome/less/path.less
