Metadata-Version: 1.1
Name: dsreports
Version: 0.1
Summary: Create static reports for Dataswim with Hugo
Home-page: https://github.com/synw/django-dsreports
Author: synw
Author-email: synwe@yahoo.com
License: UNKNOWN
Download-URL: https://github.com/synw/django-dsreports/releases/tag/0.1
Keywords: reporting
Platform: UNKNOWN
Classifier: Development Status :: 3 - Alpha
Classifier: Intended Audience :: Developers
Classifier: License :: OSI Approved :: MIT License
Classifier: Programming Language :: Python :: 3.6
